koladapy/__init__.py
koladapy/api.py
koladapy/exceptions.py
koladapy/utils.py
koladapy-1.0.1.dist-info/licenses/LICENSE.md
koladapy-1.0.1.dist-info/METADATA
koladapy-1.0.1.dist-info/WHEEL
koladapy-1.0.1.dist-info/top_level.txt
koladapy-1.0.1.dist-info/RECORD
